starhtml/__init__.py
starhtml/auth.py
starhtml/core.py
starhtml/datastar.py
starhtml/html.py
starhtml/plugins.py
starhtml/py.typed
starhtml/realtime.py
starhtml/server.py
starhtml/starapp.py
starhtml/tags.py
starhtml/utils.py
starhtml/xtend.py
starhtml/static/datastar.js
starhtml/static/js/plugins/canvas.js
starhtml/static/js/plugins/drag.js
starhtml/static/js/plugins/katex.js
starhtml/static/js/plugins/markdown.js
starhtml/static/js/plugins/mermaid.js
starhtml/static/js/plugins/persist.js
starhtml/static/js/plugins/position.js
starhtml/static/js/plugins/resize.js
starhtml/static/js/plugins/scroll.js
starhtml/static/js/plugins/smooth-scroll.js
starhtml/static/js/plugins/split.js
starhtml/static/js/plugins/throttle.js
starhtml-0.5.2.dist-info/METADATA
starhtml-0.5.2.dist-info/WHEEL
starhtml-0.5.2.dist-info/licenses/LICENSE
starhtml-0.5.2.dist-info/licenses/NOTICE
starhtml-0.5.2.dist-info/RECORD
