Metadata-Version: 2.4
Name: starhtml
Version: 0.5.2
Summary: Modern HTML generation in Python, inspired by FastHTML
License-File: LICENSE
License-File: NOTICE
Requires-Python: >=3.12
Requires-Dist: beautifulsoup4
Requires-Dist: fastcore
Requires-Dist: fastlite
Requires-Dist: httpx
Requires-Dist: itsdangerous
Requires-Dist: oauthlib
Requires-Dist: python-dateutil
Requires-Dist: python-multipart>=0.0.20
Requires-Dist: rjsmin>=1.2.4
Requires-Dist: starlette
Requires-Dist: starlette-compress>=1.0.0
Requires-Dist: uvicorn[standard]
Provides-Extra: demo
Requires-Dist: starlighter; extra == 'demo'
Provides-Extra: dev
Requires-Dist: brotli>=1.1.0; extra == 'dev'
Requires-Dist: ipykernel; extra == 'dev'
Requires-Dist: pip-tools; extra == 'dev'
Requires-Dist: psutil; extra == 'dev'
Requires-Dist: pyright; extra == 'dev'
Requires-Dist: ruff; extra == 'dev'
Provides-Extra: test
Requires-Dist: pytest; extra == 'test'
Requires-Dist: pytest-asyncio; extra == 'test'
Requires-Dist: pytest-cov>=6.1.1; extra == 'test'
Requires-Dist: pytest-timeout; extra == 'test'
Requires-Dist: pytest-watch; extra == 'test'
Requires-Dist: pytest-xdist; extra == 'test'
Requires-Dist: requests>=2.32.4; extra == 'test'
